bloret_api_tool/__init__.py
bloret_api_tool/cli.py
bloret_api_tool/core.py
bloret_api_tool-0.1.0.dist-info/licenses/LICENSE
tests/__init__.py
tests/test_cli.py
tests/test_core.py
bloret_api_tool-0.1.0.dist-info/METADATA
bloret_api_tool-0.1.0.dist-info/WHEEL
bloret_api_tool-0.1.0.dist-info/entry_points.txt
bloret_api_tool-0.1.0.dist-info/top_level.txt
bloret_api_tool-0.1.0.dist-info/RECORD
