Metadata-Version: 2.4
Name: bloret-api-tool
Version: 0.1.0
Summary: A Python library for interacting with Bloret Launcher API
Home-page: https://github.com/bloret/bloret-api-tool
Author: Bloret
Author-email: Bloret <contact@bloret.com>
License: MIT
Project-URL: Homepage, https://github.com/bloret/bloret-api-tool
Project-URL: Bug Tracker, https://github.com/bloret/bloret-api-tool/issues
Classifier: Development Status :: 3 - Alpha
Classifier: Intended Audience :: Developers
Classifier: License :: OSI Approved :: MIT License
Classifier: Operating System :: OS Independent
Classifier: Programming Language :: Python :: 3
Classifier: Programming Language :: Python :: 3.7
Classifier: Programming Language :: Python :: 3.8
Classifier: Programming Language :: Python :: 3.9
Classifier: Programming Language :: Python :: 3.10
Classifier: Programming Language :: Python :: 3.11
Requires-Python: >=3.7
License-File: LICENSE
Requires-Dist: requests>=2.25.0
Provides-Extra: dev
Requires-Dist: pytest>=6.0; extra == "dev"
Requires-Dist: pytest-cov; extra == "dev"
Requires-Dist: flake8; extra == "dev"
Dynamic: author
Dynamic: home-page
Dynamic: license-file
Dynamic: requires-python
